MANIFEST.in
README.md
setup.py
ickafka/__init__.py
ickafka/__version__.py
ickafka/cli.py
ickafka/config.py
ickafka/input.py
ickafka.egg-info/PKG-INFO
ickafka.egg-info/SOURCES.txt
ickafka.egg-info/dependency_links.txt
ickafka.egg-info/entry_points.txt
ickafka.egg-info/requires.txt
ickafka.egg-info/top_level.txt