Metadata-Version: 2.1
Name: ickafka
Version: 0.1.2
Summary: Improved Color Kafka
Home-page: https://github.com/davegallant/ickafka
Author: Dave Gallant
License: Apache License, Version 2.0
Keywords: kafka,pygments
Platform: UNKNOWN
